pympi/Elan.py
pympi/Praat.py
pympi/__init__.py
pympi_ling-1.71.dist-info/licenses/LICENSE
pympi_ling-1.71.dist-info/METADATA
pympi_ling-1.71.dist-info/WHEEL
pympi_ling-1.71.dist-info/top_level.txt
pympi_ling-1.71.dist-info/RECORD
