Metadata-Version: 2.4
Name: pympi-ling
Version: 1.71
Summary: A python module for processing ELAN and Praat annotation files
Author-email: Mart Lubbers <mart@martlubbers.net>, Francisco Torreira <francisco.torreira@mpi.nl>
Project-URL: Repository, https://github.com/dopefishh/pympi
Classifier: Development Status :: 5 - Production/Stable
Classifier: Environment :: Console
Classifier: Natural Language :: English
Classifier: Operating System :: OS Independent
Classifier: Topic :: Text Processing :: Linguistic
Requires-Python: >=3.9
License-File: LICENSE
Provides-Extra: test
Requires-Dist: pytest>=5; extra == "test"
Requires-Dist: pytest-mock; extra == "test"
Requires-Dist: pytest-cov; extra == "test"
Requires-Dist: coverage>=4.2; extra == "test"
Requires-Dist: lxml; extra == "test"
Dynamic: license-file
